sortipy/__init__.py
sortipy/sortipy.py
sortipy/exceptions/__init__.py
sortipy/exceptions/exceptions.py
sortipy/models/Directory.py
sortipy/models/File.py
sortipy/models/__init__.py
sortipy/sorters/DefaultSorter.py
sortipy/sorters/__init__.py
sortipy-0.0.5.dist-info/LICENSE
sortipy-0.0.5.dist-info/LICENSE.txt
sortipy-0.0.5.dist-info/METADATA
sortipy-0.0.5.dist-info/WHEEL
sortipy-0.0.5.dist-info/top_level.txt
sortipy-0.0.5.dist-info/RECORD
