Metadata-Version: 2.1
Name: sortipy
Version: 0.0.5
Summary: Sortipy is designed to help you organize files in a directory by sorting them based on their file extensions.
Home-page: https://github.com/pzzzl/sortipy
Author: Bruno Peselli
Author-email: brunopeselli@gmail.com
Requires-Python: >=3.6
License-File: LICENSE
License-File: LICENSE.txt
